setup.cfg
setup.py
openam/__init__.py
python_openam.egg-info/PKG-INFO
python_openam.egg-info/SOURCES.txt
python_openam.egg-info/dependency_links.txt
python_openam.egg-info/not-zip-safe
python_openam.egg-info/requires.txt
python_openam.egg-info/top_level.txt